{
  "color": {
    "zinc": {
      "50": {
        "value": "#15171c",
        "type": "color",
        "description": "1:1 contrast against root-default (#15171c)"
      },
      "100": {
        "value": "#2e323a",
        "type": "color",
        "description": "1.4:1 contrast against root-default (#15171c)"
      },
      "200": {
        "value": "#131519",
        "type": "color",
        "description": "-1.15:1 contrast against ui-active (#20242a)"
      },
      "300": {
        "value": "#191c20",
        "type": "color",
        "description": "-1.08:1 contrast against ui-active (#20242a)"
      },
      "400": {
        "value": "#20242a",
        "type": "color",
        "description": "1:1 contrast against ui-active (#20242a)"
      },
      "600": {
        "value": "#99a0ac",
        "type": "color",
        "description": "6:1 contrast against ui-active (#20242a)"
      },
      "700": {
        "value": "#8a9eed",
        "type": "color",
        "description": "7:1 contrast against root-default (#15171c)"
      },
      "800": {
        "value": "#9ea2a6",
        "type": "color",
        "description": "7:1 contrast against root-default (#15171c)"
      },
      "900": {
        "value": "#c2c4c7",
        "type": "color",
        "description": "9:1 contrast against ui-active (#20242a)"
      }
    },
    "red": {
      "50": {
        "value": "#000000",
        "type": "color",
        "description": "9:1 contrast against ui-alert-active (#df6666)"
      },
      "100": {
        "value": "#100404",
        "type": "color",
        "description": "6:1 contrast against ui-alert-active (#df6666)"
      },
      "400": {
        "value": "#ce6565",
        "type": "color",
        "description": "1.1:1 contrast against ui-alert-active (#df6666)"
      },
      "500": {
        "value": "#df6666",
        "type": "color",
        "description": "1:1 contrast against ui-alert-active (#df6666)"
      },
      "600": {
        "value": "#e26f6f",
        "type": "color",
        "description": "-1.08:1 contrast against ui-alert-active (#df6666)"
      },
      "700": {
        "value": "#e47878",
        "type": "color",
        "description": "-1.15:1 contrast against ui-alert-active (#df6666)"
      },
      "800": {
        "value": "#e78686",
        "type": "color",
        "description": "7:1 contrast against root-default (#15171c)"
      }
    },
    "blue": {
      "50": {
        "value": "#000000",
        "type": "color",
        "description": "9:1 contrast against ui-info-active (#6a8cb3)"
      },
      "100": {
        "value": "#010206",
        "type": "color",
        "description": "6:1 contrast against ui-info-active (#6a8cb3)"
      },
      "400": {
        "value": "#6885a8",
        "type": "color",
        "description": "1.1:1 contrast against ui-info-active (#6a8cb3)"
      },
      "500": {
        "value": "#6a8cb3",
        "type": "color",
        "description": "1:1 contrast against ui-info-active (#6a8cb3)"
      },
      "600": {
        "value": "#6f93bc",
        "type": "color",
        "description": "-1.08:1 contrast against ui-info-active (#6a8cb3)"
      },
      "700": {
        "value": "#7399c4",
        "type": "color",
        "description": "-1.15:1 contrast against ui-info-active (#6a8cb3)"
      },
      "900": {
        "value": "#7da5d2",
        "type": "color",
        "description": "7:1 contrast against root-default (#15171c)"
      }
    },
    "emerald": {
      "50": {
        "value": "#000000",
        "type": "color",
        "description": "9:1 contrast against ui-success-active (#58977b)"
      },
      "100": {
        "value": "#000403",
        "type": "color",
        "description": "6:1 contrast against ui-success-active (#58977b)"
      },
      "400": {
        "value": "#588e76",
        "type": "color",
        "description": "1.1:1 contrast against ui-success-active (#58977b)"
      },
      "500": {
        "value": "#58977b",
        "type": "color",
        "description": "1:1 contrast against ui-success-active (#58977b)"
      },
      "600": {
        "value": "#5c9e81",
        "type": "color",
        "description": "-1.08:1 contrast against ui-success-active (#58977b)"
      },
      "700": {
        "value": "#5fa385",
        "type": "color",
        "description": "-1.15:1 contrast against ui-success-active (#58977b)"
      },
      "900": {
        "value": "#66b08f",
        "type": "color",
        "description": "7:1 contrast against root-default (#15171c)"
      }
    },
    "stone": {
      "100": {
        "value": "#191c20",
        "type": "color",
        "description": "1:1 contrast against layer-default (#191c20)"
      },
      "200": {
        "value": "#32353d",
        "type": "color",
        "description": "1.4:1 contrast against layer-default (#191c20)"
      },
      "600": {
        "value": "#9298a4",
        "type": "color",
        "description": "6:1 contrast against layer-default (#191c20)"
      },
      "700": {
        "value": "#8ea1ed",
        "type": "color",
        "description": "7:1 contrast against layer-default (#191c20)"
      },
      "800": {
        "value": "#a2a5aa",
        "type": "color",
        "description": "7:1 contrast against layer-default (#191c20)"
      }
    },
    "neutral": {
      "100": {
        "value": "#000001",
        "type": "color",
        "description": "9:1 contrast against ui-accent-active (#a6a9ae)"
      },
      "400": {
        "value": "#262c37",
        "type": "color",
        "description": "6:1 contrast against ui-accent-active (#a6a9ae)"
      },
      "700": {
        "value": "#a0a1a4",
        "type": "color",
        "description": "1.1:1 contrast against ui-accent-active (#a6a9ae)"
      },
      "800": {
        "value": "#aeb1b6",
        "type": "color",
        "description": "-1.08:1 contrast against ui-accent-active (#a6a9ae)"
      },
      "900": {
        "value": "#b4b7bd",
        "type": "color",
        "description": "-1.15:1 contrast against ui-accent-active (#a6a9ae)"
      },
      "950": {
        "value": "#a6a9ae",
        "type": "color",
        "description": "1:1 contrast against ui-accent-active (#a6a9ae)"
      }
    },
    "slate": {
      "100": {
        "value": "#000000",
        "type": "color",
        "description": "9:1 contrast against ui-brand-active (#6a84e8)"
      },
      "400": {
        "value": "#020308",
        "type": "color",
        "description": "6:1 contrast against ui-brand-active (#6a84e8)"
      },
      "700": {
        "value": "#5f7ce8",
        "type": "color",
        "description": "1.1:1 contrast against ui-brand-active (#6a84e8)"
      },
      "800": {
        "value": "#738ce9",
        "type": "color",
        "description": "-1.08:1 contrast against ui-brand-active (#6a84e8)"
      },
      "900": {
        "value": "#7a91ea",
        "type": "color",
        "description": "-1.15:1 contrast against ui-brand-active (#6a84e8)"
      },
      "950": {
        "value": "#6a84e8",
        "type": "color",
        "description": "1:1 contrast against ui-brand-active (#6a84e8)"
      }
    }
  }
}
