{
  "inputs": {
    "../node_modules/.pnpm/@zag-js+anatomy@1.33.1/node_modules/@zag-js/anatomy/dist/index.mjs": {
      "bytes": 1168,
      "imports": [],
      "format": "esm"
    },
    "../node_modules/.pnpm/@zag-js+dom-query@1.33.1/node_modules/@zag-js/dom-query/dist/index.mjs": {
      "bytes": 51529,
      "imports": [],
      "format": "esm"
    },
    "../node_modules/.pnpm/@zag-js+utils@1.33.1/node_modules/@zag-js/utils/dist/index.mjs": {
      "bytes": 17946,
      "imports": [],
      "format": "esm"
    },
    "../node_modules/.pnpm/@zag-js+core@1.33.1/node_modules/@zag-js/core/dist/index.mjs": {
      "bytes": 3624,
      "imports": [
        {
          "path": "../node_modules/.pnpm/@zag-js+utils@1.33.1/node_modules/@zag-js/utils/dist/index.mjs",
          "kind": "import-statement",
          "original": "@zag-js/utils"
        },
        {
          "path": "../node_modules/.pnpm/@zag-js+dom-query@1.33.1/node_modules/@zag-js/dom-query/dist/index.mjs",
          "kind": "import-statement",
          "original": "@zag-js/dom-query"
        }
      ],
      "format": "esm"
    },
    "../node_modules/.pnpm/@zag-js+types@1.33.1/node_modules/@zag-js/types/dist/index.mjs": {
      "bytes": 374,
      "imports": [],
      "format": "esm"
    },
    "../node_modules/.pnpm/@zag-js+accordion@1.33.1/node_modules/@zag-js/accordion/dist/index.mjs": {
      "bytes": 10194,
      "imports": [
        {
          "path": "../node_modules/.pnpm/@zag-js+anatomy@1.33.1/node_modules/@zag-js/anatomy/dist/index.mjs",
          "kind": "import-statement",
          "original": "@zag-js/anatomy"
        },
        {
          "path": "../node_modules/.pnpm/@zag-js+dom-query@1.33.1/node_modules/@zag-js/dom-query/dist/index.mjs",
          "kind": "import-statement",
          "original": "@zag-js/dom-query"
        },
        {
          "path": "../node_modules/.pnpm/@zag-js+utils@1.33.1/node_modules/@zag-js/utils/dist/index.mjs",
          "kind": "import-statement",
          "original": "@zag-js/utils"
        },
        {
          "path": "../node_modules/.pnpm/@zag-js+core@1.33.1/node_modules/@zag-js/core/dist/index.mjs",
          "kind": "import-statement",
          "original": "@zag-js/core"
        },
        {
          "path": "../node_modules/.pnpm/@zag-js+types@1.33.1/node_modules/@zag-js/types/dist/index.mjs",
          "kind": "import-statement",
          "original": "@zag-js/types"
        }
      ],
      "format": "esm"
    },
    "../node_modules/.pnpm/proxy-compare@3.0.1/node_modules/proxy-compare/dist/index.js": {
      "bytes": 13990,
      "imports": [],
      "format": "esm"
    },
    "../node_modules/.pnpm/@zag-js+store@1.33.1/node_modules/@zag-js/store/dist/index.mjs": {
      "bytes": 10793,
      "imports": [
        {
          "path": "../node_modules/.pnpm/proxy-compare@3.0.1/node_modules/proxy-compare/dist/index.js",
          "kind": "import-statement",
          "original": "proxy-compare"
        }
      ],
      "format": "esm"
    },
    "../node_modules/.pnpm/@zag-js+vanilla@1.33.1/node_modules/@zag-js/vanilla/dist/index.mjs": {
      "bytes": 15587,
      "imports": [
        {
          "path": "../node_modules/.pnpm/@zag-js+core@1.33.1/node_modules/@zag-js/core/dist/index.mjs",
          "kind": "import-statement",
          "original": "@zag-js/core"
        },
        {
          "path": "../node_modules/.pnpm/@zag-js+core@1.33.1/node_modules/@zag-js/core/dist/index.mjs",
          "kind": "import-statement",
          "original": "@zag-js/core"
        },
        {
          "path": "../node_modules/.pnpm/@zag-js+types@1.33.1/node_modules/@zag-js/types/dist/index.mjs",
          "kind": "import-statement",
          "original": "@zag-js/types"
        },
        {
          "path": "../node_modules/.pnpm/@zag-js+store@1.33.1/node_modules/@zag-js/store/dist/index.mjs",
          "kind": "import-statement",
          "original": "@zag-js/store"
        },
        {
          "path": "../node_modules/.pnpm/@zag-js+utils@1.33.1/node_modules/@zag-js/utils/dist/index.mjs",
          "kind": "import-statement",
          "original": "@zag-js/utils"
        }
      ],
      "format": "esm"
    },
    "lib/core.ts": {
      "bytes": 1311,
      "imports": [
        {
          "path": "../node_modules/.pnpm/@zag-js+vanilla@1.33.1/node_modules/@zag-js/vanilla/dist/index.mjs",
          "kind": "import-statement",
          "original": "@zag-js/vanilla"
        }
      ],
      "format": "esm"
    },
    "components/accordion.ts": {
      "bytes": 1807,
      "imports": [
        {
          "path": "../node_modules/.pnpm/@zag-js+accordion@1.33.1/node_modules/@zag-js/accordion/dist/index.mjs",
          "kind": "import-statement",
          "original": "@zag-js/accordion"
        },
        {
          "path": "../node_modules/.pnpm/@zag-js+vanilla@1.33.1/node_modules/@zag-js/vanilla/dist/index.mjs",
          "kind": "import-statement",
          "original": "@zag-js/vanilla"
        },
        {
          "path": "lib/core.ts",
          "kind": "import-statement",
          "original": "../lib/core"
        }
      ],
      "format": "esm"
    },
    "lib/util.ts": {
      "bytes": 6185,
      "imports": [],
      "format": "esm"
    },
    "hooks/accordion.ts": {
      "bytes": 5241,
      "imports": [
        {
          "path": "components/accordion.ts",
          "kind": "import-statement",
          "original": "../components/accordion"
        },
        {
          "path": "lib/util.ts",
          "kind": "import-statement",
          "original": "../lib/util"
        }
      ],
      "format": "esm"
    },
    "../node_modules/.pnpm/@zag-js+interact-outside@1.33.1/node_modules/@zag-js/interact-outside/dist/index.mjs": {
      "bytes": 7948,
      "imports": [
        {
          "path": "../node_modules/.pnpm/@zag-js+dom-query@1.33.1/node_modules/@zag-js/dom-query/dist/index.mjs",
          "kind": "import-statement",
          "original": "@zag-js/dom-query"
        },
        {
          "path": "../node_modules/.pnpm/@zag-js+utils@1.33.1/node_modules/@zag-js/utils/dist/index.mjs",
          "kind": "import-statement",
          "original": "@zag-js/utils"
        }
      ],
      "format": "esm"
    },
    "../node_modules/.pnpm/@zag-js+dismissable@1.33.1/node_modules/@zag-js/dismissable/dist/index.mjs": {
      "bytes": 9689,
      "imports": [
        {
          "path": "../node_modules/.pnpm/@zag-js+dom-query@1.33.1/node_modules/@zag-js/dom-query/dist/index.mjs",
          "kind": "import-statement",
          "original": "@zag-js/dom-query"
        },
        {
          "path": "../node_modules/.pnpm/@zag-js+interact-outside@1.33.1/node_modules/@zag-js/interact-outside/dist/index.mjs",
          "kind": "import-statement",
          "original": "@zag-js/interact-outside"
        },
        {
          "path": "../node_modules/.pnpm/@zag-js+utils@1.33.1/node_modules/@zag-js/utils/dist/index.mjs",
          "kind": "import-statement",
          "original": "@zag-js/utils"
        }
      ],
      "format": "esm"
    },
    "../node_modules/.pnpm/@zag-js+toast@1.33.1/node_modules/@zag-js/toast/dist/index.mjs": {
      "bytes": 33010,
      "imports": [
        {
          "path": "../node_modules/.pnpm/@zag-js+dom-query@1.33.1/node_modules/@zag-js/dom-query/dist/index.mjs",
          "kind": "import-statement",
          "original": "@zag-js/dom-query"
        },
        {
          "path": "../node_modules/.pnpm/@zag-js+anatomy@1.33.1/node_modules/@zag-js/anatomy/dist/index.mjs",
          "kind": "import-statement",
          "original": "@zag-js/anatomy"
        },
        {
          "path": "../node_modules/.pnpm/@zag-js+core@1.33.1/node_modules/@zag-js/core/dist/index.mjs",
          "kind": "import-statement",
          "original": "@zag-js/core"
        },
        {
          "path": "../node_modules/.pnpm/@zag-js+dismissable@1.33.1/node_modules/@zag-js/dismissable/dist/index.mjs",
          "kind": "import-statement",
          "original": "@zag-js/dismissable"
        },
        {
          "path": "../node_modules/.pnpm/@zag-js+utils@1.33.1/node_modules/@zag-js/utils/dist/index.mjs",
          "kind": "import-statement",
          "original": "@zag-js/utils"
        }
      ],
      "format": "esm"
    },
    "components/toast.ts": {
      "bytes": 9360,
      "imports": [
        {
          "path": "../node_modules/.pnpm/@zag-js+toast@1.33.1/node_modules/@zag-js/toast/dist/index.mjs",
          "kind": "import-statement",
          "original": "@zag-js/toast"
        },
        {
          "path": "../node_modules/.pnpm/@zag-js+vanilla@1.33.1/node_modules/@zag-js/vanilla/dist/index.mjs",
          "kind": "import-statement",
          "original": "@zag-js/vanilla"
        },
        {
          "path": "lib/core.ts",
          "kind": "import-statement",
          "original": "../lib/core"
        },
        {
          "path": "lib/util.ts",
          "kind": "import-statement",
          "original": "../lib/util"
        }
      ],
      "format": "esm"
    },
    "hooks/toast.ts": {
      "bytes": 4515,
      "imports": [
        {
          "path": "components/toast.ts",
          "kind": "import-statement",
          "original": "../components/toast"
        },
        {
          "path": "lib/util.ts",
          "kind": "import-statement",
          "original": "../lib/util"
        }
      ],
      "format": "esm"
    },
    "../node_modules/.pnpm/@zag-js+toggle-group@1.33.1/node_modules/@zag-js/toggle-group/dist/index.mjs": {
      "bytes": 10833,
      "imports": [
        {
          "path": "../node_modules/.pnpm/@zag-js+anatomy@1.33.1/node_modules/@zag-js/anatomy/dist/index.mjs",
          "kind": "import-statement",
          "original": "@zag-js/anatomy"
        },
        {
          "path": "../node_modules/.pnpm/@zag-js+dom-query@1.33.1/node_modules/@zag-js/dom-query/dist/index.mjs",
          "kind": "import-statement",
          "original": "@zag-js/dom-query"
        },
        {
          "path": "../node_modules/.pnpm/@zag-js+utils@1.33.1/node_modules/@zag-js/utils/dist/index.mjs",
          "kind": "import-statement",
          "original": "@zag-js/utils"
        },
        {
          "path": "../node_modules/.pnpm/@zag-js+core@1.33.1/node_modules/@zag-js/core/dist/index.mjs",
          "kind": "import-statement",
          "original": "@zag-js/core"
        },
        {
          "path": "../node_modules/.pnpm/@zag-js+types@1.33.1/node_modules/@zag-js/types/dist/index.mjs",
          "kind": "import-statement",
          "original": "@zag-js/types"
        }
      ],
      "format": "esm"
    },
    "components/toggle-group.ts": {
      "bytes": 1187,
      "imports": [
        {
          "path": "../node_modules/.pnpm/@zag-js+toggle-group@1.33.1/node_modules/@zag-js/toggle-group/dist/index.mjs",
          "kind": "import-statement",
          "original": "@zag-js/toggle-group"
        },
        {
          "path": "../node_modules/.pnpm/@zag-js+vanilla@1.33.1/node_modules/@zag-js/vanilla/dist/index.mjs",
          "kind": "import-statement",
          "original": "@zag-js/vanilla"
        },
        {
          "path": "lib/core.ts",
          "kind": "import-statement",
          "original": "../lib/core"
        },
        {
          "path": "lib/util.ts",
          "kind": "import-statement",
          "original": "../lib/util"
        }
      ],
      "format": "esm"
    },
    "hooks/toggle-group.ts": {
      "bytes": 4095,
      "imports": [
        {
          "path": "components/toggle-group.ts",
          "kind": "import-statement",
          "original": "../components/toggle-group"
        },
        {
          "path": "lib/util.ts",
          "kind": "import-statement",
          "original": "../lib/util"
        }
      ],
      "format": "esm"
    },
    "../node_modules/.pnpm/@zag-js+collection@1.33.1/node_modules/@zag-js/collection/dist/index.mjs": {
      "bytes": 52076,
      "imports": [
        {
          "path": "../node_modules/.pnpm/@zag-js+utils@1.33.1/node_modules/@zag-js/utils/dist/index.mjs",
          "kind": "import-statement",
          "original": "@zag-js/utils"
        }
      ],
      "format": "esm"
    },
    "../node_modules/.pnpm/@floating-ui+utils@0.2.10/node_modules/@floating-ui/utils/dist/floating-ui.utils.mjs": {
      "bytes": 4201,
      "imports": [],
      "format": "esm"
    },
    "../node_modules/.pnpm/@floating-ui+core@1.7.4/node_modules/@floating-ui/core/dist/floating-ui.core.mjs": {
      "bytes": 36443,
      "imports": [
        {
          "path": "../node_modules/.pnpm/@floating-ui+utils@0.2.10/node_modules/@floating-ui/utils/dist/floating-ui.utils.mjs",
          "kind": "import-statement",
          "original": "@floating-ui/utils"
        },
        {
          "path": "../node_modules/.pnpm/@floating-ui+utils@0.2.10/node_modules/@floating-ui/utils/dist/floating-ui.utils.mjs",
          "kind": "import-statement",
          "original": "@floating-ui/utils"
        }
      ],
      "format": "esm"
    },
    "../node_modules/.pnpm/@floating-ui+utils@0.2.10/node_modules/@floating-ui/utils/dist/floating-ui.utils.dom.mjs": {
      "bytes": 6219,
      "imports": [],
      "format": "esm"
    },
    "../node_modules/.pnpm/@floating-ui+dom@1.7.5/node_modules/@floating-ui/dom/dist/floating-ui.dom.mjs": {
      "bytes": 27498,
      "imports": [
        {
          "path": "../node_modules/.pnpm/@floating-ui+core@1.7.4/node_modules/@floating-ui/core/dist/floating-ui.core.mjs",
          "kind": "import-statement",
          "original": "@floating-ui/core"
        },
        {
          "path": "../node_modules/.pnpm/@floating-ui+utils@0.2.10/node_modules/@floating-ui/utils/dist/floating-ui.utils.mjs",
          "kind": "import-statement",
          "original": "@floating-ui/utils"
        },
        {
          "path": "../node_modules/.pnpm/@floating-ui+utils@0.2.10/node_modules/@floating-ui/utils/dist/floating-ui.utils.dom.mjs",
          "kind": "import-statement",
          "original": "@floating-ui/utils/dom"
        },
        {
          "path": "../node_modules/.pnpm/@floating-ui+utils@0.2.10/node_modules/@floating-ui/utils/dist/floating-ui.utils.dom.mjs",
          "kind": "import-statement",
          "original": "@floating-ui/utils/dom"
        }
      ],
      "format": "esm"
    },
    "../node_modules/.pnpm/@zag-js+popper@1.33.1/node_modules/@zag-js/popper/dist/index.mjs": {
      "bytes": 12025,
      "imports": [
        {
          "path": "../node_modules/.pnpm/@floating-ui+dom@1.7.5/node_modules/@floating-ui/dom/dist/floating-ui.dom.mjs",
          "kind": "import-statement",
          "original": "@floating-ui/dom"
        },
        {
          "path": "../node_modules/.pnpm/@zag-js+dom-query@1.33.1/node_modules/@zag-js/dom-query/dist/index.mjs",
          "kind": "import-statement",
          "original": "@zag-js/dom-query"
        },
        {
          "path": "../node_modules/.pnpm/@zag-js+utils@1.33.1/node_modules/@zag-js/utils/dist/index.mjs",
          "kind": "import-statement",
          "original": "@zag-js/utils"
        }
      ],
      "format": "esm"
    },
    "../node_modules/.pnpm/@zag-js+select@1.33.1/node_modules/@zag-js/select/dist/index.mjs": {
      "bytes": 39831,
      "imports": [
        {
          "path": "../node_modules/.pnpm/@zag-js+anatomy@1.33.1/node_modules/@zag-js/anatomy/dist/index.mjs",
          "kind": "import-statement",
          "original": "@zag-js/anatomy"
        },
        {
          "path": "../node_modules/.pnpm/@zag-js+collection@1.33.1/node_modules/@zag-js/collection/dist/index.mjs",
          "kind": "import-statement",
          "original": "@zag-js/collection"
        },
        {
          "path": "../node_modules/.pnpm/@zag-js+dom-query@1.33.1/node_modules/@zag-js/dom-query/dist/index.mjs",
          "kind": "import-statement",
          "original": "@zag-js/dom-query"
        },
        {
          "path": "../node_modules/.pnpm/@zag-js+popper@1.33.1/node_modules/@zag-js/popper/dist/index.mjs",
          "kind": "import-statement",
          "original": "@zag-js/popper"
        },
        {
          "path": "../node_modules/.pnpm/@zag-js+utils@1.33.1/node_modules/@zag-js/utils/dist/index.mjs",
          "kind": "import-statement",
          "original": "@zag-js/utils"
        },
        {
          "path": "../node_modules/.pnpm/@zag-js+core@1.33.1/node_modules/@zag-js/core/dist/index.mjs",
          "kind": "import-statement",
          "original": "@zag-js/core"
        },
        {
          "path": "../node_modules/.pnpm/@zag-js+dismissable@1.33.1/node_modules/@zag-js/dismissable/dist/index.mjs",
          "kind": "import-statement",
          "original": "@zag-js/dismissable"
        },
        {
          "path": "../node_modules/.pnpm/@zag-js+types@1.33.1/node_modules/@zag-js/types/dist/index.mjs",
          "kind": "import-statement",
          "original": "@zag-js/types"
        }
      ],
      "format": "esm"
    },
    "components/select.ts": {
      "bytes": 7695,
      "imports": [
        {
          "path": "../node_modules/.pnpm/@zag-js+select@1.33.1/node_modules/@zag-js/select/dist/index.mjs",
          "kind": "import-statement",
          "original": "@zag-js/select"
        },
        {
          "path": "../node_modules/.pnpm/@zag-js+select@1.33.1/node_modules/@zag-js/select/dist/index.mjs",
          "kind": "import-statement",
          "original": "@zag-js/select"
        },
        {
          "path": "../node_modules/.pnpm/@zag-js+vanilla@1.33.1/node_modules/@zag-js/vanilla/dist/index.mjs",
          "kind": "import-statement",
          "original": "@zag-js/vanilla"
        },
        {
          "path": "lib/core.ts",
          "kind": "import-statement",
          "original": "../lib/core"
        },
        {
          "path": "lib/util.ts",
          "kind": "import-statement",
          "original": "../lib/util"
        }
      ],
      "format": "esm"
    },
    "hooks/select.ts": {
      "bytes": 5865,
      "imports": [
        {
          "path": "components/select.ts",
          "kind": "import-statement",
          "original": "../components/select"
        },
        {
          "path": "lib/util.ts",
          "kind": "import-statement",
          "original": "../lib/util"
        }
      ],
      "format": "esm"
    },
    "../node_modules/.pnpm/@zag-js+focus-visible@1.33.1/node_modules/@zag-js/focus-visible/dist/index.mjs": {
      "bytes": 6071,
      "imports": [
        {
          "path": "../node_modules/.pnpm/@zag-js+dom-query@1.33.1/node_modules/@zag-js/dom-query/dist/index.mjs",
          "kind": "import-statement",
          "original": "@zag-js/dom-query"
        }
      ],
      "format": "esm"
    },
    "../node_modules/.pnpm/@zag-js+switch@1.33.1/node_modules/@zag-js/switch/dist/index.mjs": {
      "bytes": 8837,
      "imports": [
        {
          "path": "../node_modules/.pnpm/@zag-js+anatomy@1.33.1/node_modules/@zag-js/anatomy/dist/index.mjs",
          "kind": "import-statement",
          "original": "@zag-js/anatomy"
        },
        {
          "path": "../node_modules/.pnpm/@zag-js+dom-query@1.33.1/node_modules/@zag-js/dom-query/dist/index.mjs",
          "kind": "import-statement",
          "original": "@zag-js/dom-query"
        },
        {
          "path": "../node_modules/.pnpm/@zag-js+focus-visible@1.33.1/node_modules/@zag-js/focus-visible/dist/index.mjs",
          "kind": "import-statement",
          "original": "@zag-js/focus-visible"
        },
        {
          "path": "../node_modules/.pnpm/@zag-js+core@1.33.1/node_modules/@zag-js/core/dist/index.mjs",
          "kind": "import-statement",
          "original": "@zag-js/core"
        },
        {
          "path": "../node_modules/.pnpm/@zag-js+types@1.33.1/node_modules/@zag-js/types/dist/index.mjs",
          "kind": "import-statement",
          "original": "@zag-js/types"
        },
        {
          "path": "../node_modules/.pnpm/@zag-js+utils@1.33.1/node_modules/@zag-js/utils/dist/index.mjs",
          "kind": "import-statement",
          "original": "@zag-js/utils"
        }
      ],
      "format": "esm"
    },
    "components/switch.ts": {
      "bytes": 1467,
      "imports": [
        {
          "path": "../node_modules/.pnpm/@zag-js+switch@1.33.1/node_modules/@zag-js/switch/dist/index.mjs",
          "kind": "import-statement",
          "original": "@zag-js/switch"
        },
        {
          "path": "../node_modules/.pnpm/@zag-js+vanilla@1.33.1/node_modules/@zag-js/vanilla/dist/index.mjs",
          "kind": "import-statement",
          "original": "@zag-js/vanilla"
        },
        {
          "path": "lib/core.ts",
          "kind": "import-statement",
          "original": "../lib/core"
        }
      ],
      "format": "esm"
    },
    "hooks/switch.ts": {
      "bytes": 4878,
      "imports": [
        {
          "path": "components/switch.ts",
          "kind": "import-statement",
          "original": "../components/switch"
        },
        {
          "path": "lib/util.ts",
          "kind": "import-statement",
          "original": "../lib/util"
        }
      ],
      "format": "esm"
    },
    "../node_modules/.pnpm/@zag-js+combobox@1.33.1/node_modules/@zag-js/combobox/dist/index.mjs": {
      "bytes": 53328,
      "imports": [
        {
          "path": "../node_modules/.pnpm/@zag-js+anatomy@1.33.1/node_modules/@zag-js/anatomy/dist/index.mjs",
          "kind": "import-statement",
          "original": "@zag-js/anatomy"
        },
        {
          "path": "../node_modules/.pnpm/@zag-js+collection@1.33.1/node_modules/@zag-js/collection/dist/index.mjs",
          "kind": "import-statement",
          "original": "@zag-js/collection"
        },
        {
          "path": "../node_modules/.pnpm/@zag-js+dom-query@1.33.1/node_modules/@zag-js/dom-query/dist/index.mjs",
          "kind": "import-statement",
          "original": "@zag-js/dom-query"
        },
        {
          "path": "../node_modules/.pnpm/@zag-js+popper@1.33.1/node_modules/@zag-js/popper/dist/index.mjs",
          "kind": "import-statement",
          "original": "@zag-js/popper"
        },
        {
          "path": "../node_modules/.pnpm/@zag-js+utils@1.33.1/node_modules/@zag-js/utils/dist/index.mjs",
          "kind": "import-statement",
          "original": "@zag-js/utils"
        },
        {
          "path": "../node_modules/.pnpm/@zag-js+core@1.33.1/node_modules/@zag-js/core/dist/index.mjs",
          "kind": "import-statement",
          "original": "@zag-js/core"
        },
        {
          "path": "../node_modules/.pnpm/@zag-js+dismissable@1.33.1/node_modules/@zag-js/dismissable/dist/index.mjs",
          "kind": "import-statement",
          "original": "@zag-js/dismissable"
        },
        {
          "path": "../node_modules/.pnpm/@zag-js+types@1.33.1/node_modules/@zag-js/types/dist/index.mjs",
          "kind": "import-statement",
          "original": "@zag-js/types"
        }
      ],
      "format": "esm"
    },
    "components/combobox.ts": {
      "bytes": 7179,
      "imports": [
        {
          "path": "../node_modules/.pnpm/@zag-js+combobox@1.33.1/node_modules/@zag-js/combobox/dist/index.mjs",
          "kind": "import-statement",
          "original": "@zag-js/combobox"
        },
        {
          "path": "../node_modules/.pnpm/@zag-js+combobox@1.33.1/node_modules/@zag-js/combobox/dist/index.mjs",
          "kind": "import-statement",
          "original": "@zag-js/combobox"
        },
        {
          "path": "../node_modules/.pnpm/@zag-js+vanilla@1.33.1/node_modules/@zag-js/vanilla/dist/index.mjs",
          "kind": "import-statement",
          "original": "@zag-js/vanilla"
        },
        {
          "path": "lib/core.ts",
          "kind": "import-statement",
          "original": "../lib/core"
        },
        {
          "path": "@zag-js/combobox",
          "kind": "import-statement",
          "external": true
        }
      ],
      "format": "esm"
    },
    "hooks/combobox.ts": {
      "bytes": 6139,
      "imports": [
        {
          "path": "components/combobox.ts",
          "kind": "import-statement",
          "original": "../components/combobox"
        },
        {
          "path": "lib/util.ts",
          "kind": "import-statement",
          "original": "../lib/util"
        }
      ],
      "format": "esm"
    },
    "../node_modules/.pnpm/@zag-js+checkbox@1.33.1/node_modules/@zag-js/checkbox/dist/index.mjs": {
      "bytes": 9181,
      "imports": [
        {
          "path": "../node_modules/.pnpm/@zag-js+anatomy@1.33.1/node_modules/@zag-js/anatomy/dist/index.mjs",
          "kind": "import-statement",
          "original": "@zag-js/anatomy"
        },
        {
          "path": "../node_modules/.pnpm/@zag-js+dom-query@1.33.1/node_modules/@zag-js/dom-query/dist/index.mjs",
          "kind": "import-statement",
          "original": "@zag-js/dom-query"
        },
        {
          "path": "../node_modules/.pnpm/@zag-js+focus-visible@1.33.1/node_modules/@zag-js/focus-visible/dist/index.mjs",
          "kind": "import-statement",
          "original": "@zag-js/focus-visible"
        },
        {
          "path": "../node_modules/.pnpm/@zag-js+core@1.33.1/node_modules/@zag-js/core/dist/index.mjs",
          "kind": "import-statement",
          "original": "@zag-js/core"
        },
        {
          "path": "../node_modules/.pnpm/@zag-js+types@1.33.1/node_modules/@zag-js/types/dist/index.mjs",
          "kind": "import-statement",
          "original": "@zag-js/types"
        },
        {
          "path": "../node_modules/.pnpm/@zag-js+utils@1.33.1/node_modules/@zag-js/utils/dist/index.mjs",
          "kind": "import-statement",
          "original": "@zag-js/utils"
        }
      ],
      "format": "esm"
    },
    "components/checkbox.ts": {
      "bytes": 1515,
      "imports": [
        {
          "path": "../node_modules/.pnpm/@zag-js+checkbox@1.33.1/node_modules/@zag-js/checkbox/dist/index.mjs",
          "kind": "import-statement",
          "original": "@zag-js/checkbox"
        },
        {
          "path": "../node_modules/.pnpm/@zag-js+vanilla@1.33.1/node_modules/@zag-js/vanilla/dist/index.mjs",
          "kind": "import-statement",
          "original": "@zag-js/vanilla"
        },
        {
          "path": "lib/core.ts",
          "kind": "import-statement",
          "original": "../lib/core"
        }
      ],
      "format": "esm"
    },
    "hooks/checkbox.ts": {
      "bytes": 6132,
      "imports": [
        {
          "path": "components/checkbox.ts",
          "kind": "import-statement",
          "original": "../components/checkbox"
        },
        {
          "path": "lib/util.ts",
          "kind": "import-statement",
          "original": "../lib/util"
        }
      ],
      "format": "esm"
    },
    "hooks/corex.ts": {
      "bytes": 687,
      "imports": [
        {
          "path": "hooks/accordion.ts",
          "kind": "import-statement",
          "original": "./accordion"
        },
        {
          "path": "hooks/toast.ts",
          "kind": "import-statement",
          "original": "./toast"
        },
        {
          "path": "hooks/toggle-group.ts",
          "kind": "import-statement",
          "original": "./toggle-group"
        },
        {
          "path": "hooks/select.ts",
          "kind": "import-statement",
          "original": "./select"
        },
        {
          "path": "hooks/switch.ts",
          "kind": "import-statement",
          "original": "./switch"
        },
        {
          "path": "hooks/combobox.ts",
          "kind": "import-statement",
          "original": "./combobox"
        },
        {
          "path": "hooks/checkbox.ts",
          "kind": "import-statement",
          "original": "./checkbox"
        },
        {
          "path": "hooks/accordion.ts",
          "kind": "import-statement",
          "original": "./accordion"
        },
        {
          "path": "hooks/toast.ts",
          "kind": "import-statement",
          "original": "./toast"
        },
        {
          "path": "hooks/toggle-group.ts",
          "kind": "import-statement",
          "original": "./toggle-group"
        },
        {
          "path": "hooks/select.ts",
          "kind": "import-statement",
          "original": "./select"
        },
        {
          "path": "hooks/switch.ts",
          "kind": "import-statement",
          "original": "./switch"
        },
        {
          "path": "hooks/combobox.ts",
          "kind": "import-statement",
          "original": "./combobox"
        },
        {
          "path": "hooks/checkbox.ts",
          "kind": "import-statement",
          "original": "./checkbox"
        }
      ],
      "format": "esm"
    }
  },
  "outputs": {
    "../priv/static/corex.cjs.js.map": {
      "imports": [],
      "exports": [],
      "inputs": {},
      "bytes": 814329
    },
    "../priv/static/corex.cjs.js": {
      "imports": [],
      "exports": [],
      "entryPoint": "hooks/corex.ts",
      "inputs": {
        "hooks/corex.ts": {
          "bytesInOutput": 554
        },
        "../node_modules/.pnpm/@zag-js+anatomy@1.33.1/node_modules/@zag-js/anatomy/dist/index.mjs": {
          "bytesInOutput": 1123
        },
        "../node_modules/.pnpm/@zag-js+dom-query@1.33.1/node_modules/@zag-js/dom-query/dist/index.mjs": {
          "bytesInOutput": 27094
        },
        "../node_modules/.pnpm/@zag-js+utils@1.33.1/node_modules/@zag-js/utils/dist/index.mjs": {
          "bytesInOutput": 7524
        },
        "../node_modules/.pnpm/@zag-js+core@1.33.1/node_modules/@zag-js/core/dist/index.mjs": {
          "bytesInOutput": 1543
        },
        "../node_modules/.pnpm/@zag-js+types@1.33.1/node_modules/@zag-js/types/dist/index.mjs": {
          "bytesInOutput": 290
        },
        "../node_modules/.pnpm/@zag-js+accordion@1.33.1/node_modules/@zag-js/accordion/dist/index.mjs": {
          "bytesInOutput": 9750
        },
        "../node_modules/.pnpm/proxy-compare@3.0.1/node_modules/proxy-compare/dist/index.js": {
          "bytesInOutput": 530
        },
        "../node_modules/.pnpm/@zag-js+store@1.33.1/node_modules/@zag-js/store/dist/index.mjs": {
          "bytesInOutput": 8068
        },
        "../node_modules/.pnpm/@zag-js+vanilla@1.33.1/node_modules/@zag-js/vanilla/dist/index.mjs": {
          "bytesInOutput": 15231
        },
        "lib/core.ts": {
          "bytesInOutput": 653
        },
        "components/accordion.ts": {
          "bytesInOutput": 1499
        },
        "lib/util.ts": {
          "bytesInOutput": 1061
        },
        "hooks/accordion.ts": {
          "bytesInOutput": 4087
        },
        "../node_modules/.pnpm/@zag-js+interact-outside@1.33.1/node_modules/@zag-js/interact-outside/dist/index.mjs": {
          "bytesInOutput": 7586
        },
        "../node_modules/.pnpm/@zag-js+dismissable@1.33.1/node_modules/@zag-js/dismissable/dist/index.mjs": {
          "bytesInOutput": 9313
        },
        "../node_modules/.pnpm/@zag-js+toast@1.33.1/node_modules/@zag-js/toast/dist/index.mjs": {
          "bytesInOutput": 32573
        },
        "components/toast.ts": {
          "bytesInOutput": 6519
        },
        "hooks/toast.ts": {
          "bytesInOutput": 3232
        },
        "../node_modules/.pnpm/@zag-js+toggle-group@1.33.1/node_modules/@zag-js/toggle-group/dist/index.mjs": {
          "bytesInOutput": 10359
        },
        "components/toggle-group.ts": {
          "bytesInOutput": 822
        },
        "hooks/toggle-group.ts": {
          "bytesInOutput": 3073
        },
        "../node_modules/.pnpm/@zag-js+collection@1.33.1/node_modules/@zag-js/collection/dist/index.mjs": {
          "bytesInOutput": 13799
        },
        "../node_modules/.pnpm/@floating-ui+utils@0.2.10/node_modules/@floating-ui/utils/dist/floating-ui.utils.mjs": {
          "bytesInOutput": 3549
        },
        "../node_modules/.pnpm/@floating-ui+core@1.7.4/node_modules/@floating-ui/core/dist/floating-ui.core.mjs": {
          "bytesInOutput": 23677
        },
        "../node_modules/.pnpm/@floating-ui+utils@0.2.10/node_modules/@floating-ui/utils/dist/floating-ui.utils.dom.mjs": {
          "bytesInOutput": 5565
        },
        "../node_modules/.pnpm/@floating-ui+dom@1.7.5/node_modules/@floating-ui/dom/dist/floating-ui.dom.mjs": {
          "bytesInOutput": 20584
        },
        "../node_modules/.pnpm/@zag-js+popper@1.33.1/node_modules/@zag-js/popper/dist/index.mjs": {
          "bytesInOutput": 11411
        },
        "../node_modules/.pnpm/@zag-js+select@1.33.1/node_modules/@zag-js/select/dist/index.mjs": {
          "bytesInOutput": 39043
        },
        "components/select.ts": {
          "bytesInOutput": 6546
        },
        "hooks/select.ts": {
          "bytesInOutput": 4578
        },
        "../node_modules/.pnpm/@zag-js+focus-visible@1.33.1/node_modules/@zag-js/focus-visible/dist/index.mjs": {
          "bytesInOutput": 5332
        },
        "../node_modules/.pnpm/@zag-js+switch@1.33.1/node_modules/@zag-js/switch/dist/index.mjs": {
          "bytesInOutput": 8306
        },
        "components/switch.ts": {
          "bytesInOutput": 1136
        },
        "hooks/switch.ts": {
          "bytesInOutput": 3905
        },
        "../node_modules/.pnpm/@zag-js+combobox@1.33.1/node_modules/@zag-js/combobox/dist/index.mjs": {
          "bytesInOutput": 52662
        },
        "components/combobox.ts": {
          "bytesInOutput": 5605
        },
        "hooks/combobox.ts": {
          "bytesInOutput": 4863
        },
        "../node_modules/.pnpm/@zag-js+checkbox@1.33.1/node_modules/@zag-js/checkbox/dist/index.mjs": {
          "bytesInOutput": 8665
        },
        "components/checkbox.ts": {
          "bytesInOutput": 1211
        },
        "hooks/checkbox.ts": {
          "bytesInOutput": 4881
        }
      },
      "bytes": 381377
    }
  }
}
